Metadata-Version: 2.1
Name: logger-module
Version: 1.2
Summary: A module for logging status messages
Home-page: https://github.com/Byron0x7D2/logger-module
Author: Byron Anemogiannis
Author-email: bgane@di.uoa.gr
License: MIT
Classifier: Development Status :: 5 - Production/Stable
Classifier: Intended Audience :: Developers
Classifier: License :: OSI Approved :: MIT License
Classifier: Programming Language :: Python :: 3
Classifier: Programming Language :: Python :: 3.6
Classifier: Programming Language :: Python :: 3.7
Classifier: Programming Language :: Python :: 3.8
Classifier: Programming Language :: Python :: 3.9
Classifier: Programming Language :: Python :: 3.10
Classifier: Programming Language :: Python :: 3.11
Classifier: Operating System :: OS Independent
